pyrtk/__init__.py
pyrtk/pyrtk.py
pyrtk/rtk.py
PyRTK-1.5.dist-info/LICENSE
PyRTK-1.5.dist-info/METADATA
PyRTK-1.5.dist-info/WHEEL
PyRTK-1.5.dist-info/top_level.txt
PyRTK-1.5.dist-info/RECORD
