Metadata-Version: 2.1
Name: PyRTK
Version: 1.5
Summary: PyRTK allows you to create and decode refresh tokens for JWT authentication systems
Home-page: https://github.com/jdraiv/PyRTK/tree/master
Author: Jdraiv
Author-email: UNKNOWN
License: UNKNOWN
Platform: UNKNOWN
Classifier: Programming Language :: Python :: 3
Classifier: License :: OSI Approved :: MIT License
Classifier: Operating System :: OS Independent
Requires-Dist: cryptography
